[
    {
        "name": "Discord",
        "image": "/assets/img/discord.png",
        "source": "/service/hvtrs8%2F-dksaopd%2Ccmm-lmgkn"
    },
    {
        "name": "Movies",
        "image": "/assets/img/movies.png",
        "source": "//movie-web.app"
    },
    {
        "name": "Prime Video",
        "image": "https://play-lh.googleusercontent.com/Y7drWZZo_F2GBE1RhjR1irOkE3yrtPorHS1U9YkLKAu1DnTjQ8gNbcRmrBtkd3tnHQ",
        "source": "/service/hvtrs8%2F-wuw%2Caoaxol.aoo%2Fcp-skglil%3Fmpgnkd%2Cpcpg.oaz_cuvh%5Daee%3F0%24orelif.pevupn%5Dtm%3Djtvpq%251A'2D%250Fla%2Cppioetifem.aoo%250Fcuvh'2Drgtwrl%250Fped%251Dcv%5Dawtj_cp'3D_v%251Dqg0w4aFJ%5BrgyF5S7%3BNF0xsGG%3Ajps2uwtX-Q4G4JIIfNAzACACASACACBnS6Y%5DcoF1ACACARgUC%3BWdHJ8kB%2FonH%5DE%3BxS%2506noaavimn'3F%250Fmfdeps'2Dnmnrrkmghmmgpcgg%251Fped_'273Favv%5Ddr_ov%5Dc%5D9xZ%3AD0_jm%5Dhmm%24orelif.kdgnvivy%3Fhvtr%251A'2D%250Fqpgcq.mpgnkd%2Cngt'2Dawtj%250F0.2%250Fkdgnvidigr%5Dsglgcv%26ccaownvSvavuqPmlkc%7B%3DR1%24orelif.csqoa_jaldne%3Faozl_rrkmg_tifem_qsm_ws%24orelif.oofe%3Fcjeakkd%5Dsgtwp%24sktgSvave%3F112%2F7%3A62674%2F3682227%24lcneucgg%3Dgn%5DUQ%26mpgnkd%2Ccnakmgd%5Dif%3Djtvp'3C%250F'2Dsreas%2Corelif.lev%250Fcuvh'2D2%2C0'2Difeltkfkep_qeneat%24orelif.ls%3Fhvtr%251A'2D%250Fqpgcq.mpgnkd%2Cngt'2Dawtj%250F0.2-"
    },
    {
        "name": "Tiktok",
        "image": "/assets/img/tiktok.png",
        "source": "/service/hvtrs8%2F-wuw%2Ctkkvoi.aoo%2Fgn-"
    },
    {
        "name": "Twitch",
        "image": "/assets/img/twitch.png",
        "source": "/service/hvtrs8%2F-wuw%2Ctuivcj.vv-"
    },
    {
        "name": "Youtube",
        "image": "/assets/img/youtube.png",
        "source": "/service/hvtrs8%2F-wuw%2Cymuvu%60e%2Ccmm-"
    }
]
