[
    {
        "name": "Discord",
        "image": "/assets/img/discord.png",
        "source": "/service/hvtrs8%2F-dksaopd%2Ccmm-lmgkn"
    },
    {
        "name": "Reddit",
        "image": "/assets/img/reddit.png",
        "source": "/service/hvtrs8%2F-wuw%2Crgdfiv.aoo%2F%3Drft%3F40003"
    },
    {
        "name": "Tiktok",
        "image": "/assets/img/tiktok.png",
        "source": "/service/hvtrs8%2F-wuw%2Ctkkvoi.aoo%2Fgn-"
    },
    {
        "name": "Twitch",
        "image": "/assets/img/twitch.png",
        "source": "/service/hvtrs8%2F-wuw%2Ctuivcj.vv-"
    },
    {
        "name": "Twitter",
        "image": "/assets/img/twitter.png",
        "source": "/service/hvtrs8%2F-tuivtgr%2Ccmm-"
    },
    {
        "name": "Youtube",
        "image": "/assets/img/youtube.png",
        "source": "/service/hvtrs8%2F-wuw%2Cymuvu%60e%2Ccmm-"
    },
    {
        "name": "Spotify",
        "image": "/assets/img/spotify.png",
        "source": "/service/hvtrs8%2F-orel.qpmtkf%7B.aoo%2F"
    },
    {
        "name": "GeForce Now",
        "image": "/assets/img/gnow.png",
        "source": "/service/hvtrs8%2F-lmgkn%2Cntgq.lvkdka%2Ccmm-ut%2Fqepvkcg%2Fjvvrq8'2D-nmekl%250Clteq%2Cltkfkc%250Camo--v3%2Fnoeil%2Fkdgnvidigr%3Dppedeprgd%5Dntific%3Dvrwe%24cmnvezt%3FIlivicl%24tjeoe%3FNmip%26noaane%3Fel-WS%24ppoopv%3Dqeneat%5Daacmult%24kgy%3Fe%7BJjbEckOkJKUxI3NkJ%3B.gyHzXSK6KnT3OkaiNCH0%602vl%60knkKjmiOTG1MDK0LDK1LjWxMDCyMTOxOiKsKm%3B0KjmiOTG1MDK0LDK1LjWzLDewLjWyMCKsKmT4aCK6OT%5B5LjOwOza0MSuicWD0KjmxLji2OjG3OzS5NCHqfGiiMiK3OGLjLDnkXC2zOjWyNTPkXm%5BtMTi0Xi20LzLmLmOw%5BmKzL2WidQ%2C4hesdLB1iVIol50Pzi8%5BeGfEELJ%60o7NtssdqG%3BdrGkg%24cnignv_kd%3F3304721%3B2030346711"
    }
]